fer/__init__.py
fer/classes.py
fer/emotionsmultilanguage.py
fer/fer.py
fer/utils.py
fer/data/emotion_model.hdf5
fer/data/haarcascade_frontalface_default.xml
fer/exceptions/__init__.py
fer-25.10.2.dist-info/licenses/LICENSE
fer-25.10.2.dist-info/METADATA
fer-25.10.2.dist-info/WHEEL
fer-25.10.2.dist-info/top_level.txt
fer-25.10.2.dist-info/RECORD
