Metadata-Version: 2.4
Name: fer
Version: 25.10.2
Summary: Facial expression recognition from images
Home-page: https://github.com/justinshenk/fer
Author: Justin Shenk
Author-email: Justin Shenk <shenkjustin@gmail.com>
Maintainer: Justin Shenk
Maintainer-email: Justin Shenk <shenkjustin@gmail.com>
License: MIT
Project-URL: Homepage, https://github.com/justinshenk/fer
Project-URL: Documentation, https://github.com/justinshenk/fer
Project-URL: Bug Tracker, https://github.com/justinshenk/fer/issues
Project-URL: Source Code, https://github.com/justinshenk/fer
Keywords: facial expressions,emotion detection,faces,images
Classifier: Intended Audience :: Developers
Classifier: License :: OSI Approved :: MIT License
Classifier: Intended Audience :: Education
Classifier: Intended Audience :: Science/Research
Classifier: Programming Language :: Python :: 3
Classifier: Programming Language :: Python :: 3.8
Classifier: Programming Language :: Python :: 3.9
Classifier: Programming Language :: Python :: 3.10
Classifier: Programming Language :: Python :: 3.11
Classifier: Programming Language :: Python :: 3.12
Classifier: Topic :: Scientific/Engineering :: Mathematics
Classifier: Topic :: Software Development :: Libraries :: Python Modules
Classifier: Topic :: Software Development :: Libraries
Requires-Python: >= 3.8
License-File: LICENSE
Requires-Dist: matplotlib
Requires-Dist: opencv-contrib-python
Requires-Dist: tensorflow>=2.0.0
Requires-Dist: pandas
Requires-Dist: requests
Requires-Dist: facenet-pytorch
Requires-Dist: tqdm>=4.62.1
Requires-Dist: moviepy<2.0,>=1.0.3
Requires-Dist: ffmpeg-python>=0.2.0
Requires-Dist: Pillow
Provides-Extra: dev
Requires-Dist: pytest; extra == "dev"
Requires-Dist: coverage; extra == "dev"
Requires-Dist: sphinx; extra == "dev"
Requires-Dist: wheel; extra == "dev"
Requires-Dist: pre-commit; extra == "dev"
Requires-Dist: black; extra == "dev"
Requires-Dist: ruff; extra == "dev"
Requires-Dist: mypy; extra == "dev"
Requires-Dist: click; extra == "dev"
Provides-Extra: docs
Requires-Dist: sphinx; extra == "docs"
Provides-Extra: tests
Requires-Dist: coverage; extra == "tests"
Requires-Dist: pytest; extra == "tests"
Dynamic: author
Dynamic: home-page
Dynamic: license-file
Dynamic: maintainer
Dynamic: requires-python
